guideID/_GuideID.py
guideID/__init__.py
guideID-0.0.12.dist-info/LICENSE
guideID-0.0.12.dist-info/METADATA
guideID-0.0.12.dist-info/WHEEL
guideID-0.0.12.dist-info/top_level.txt
guideID-0.0.12.dist-info/RECORD
